{
	"info": {
		"_postman_id": "6f6aa8f8-cc71-45ba-b263-d3d607325c9b",
		"name": "omagad",
		"schema": "https://schema.getpostman.com/json/collection/v2.1.0/collection.json",
		"_exporter_id": "32602559"
	},
	"item": [
		{
			"name": "register",
			"request": {
				"method": "POST",
				"header": [],
				"body": {
					"mode": "raw",
					"raw": "{\r\n    \"username\": \"abdabdbadbadbabdfafbaf\",\r\n    \"email\": \"agaga@gmail.com\",\r\n    \"password\":\"makaka\"\r\n\r\n}",
					"options": {
						"raw": {
							"language": "json"
						}
					}
				},
				"url": {
					"raw": "http://localhost:5040/api/taskmanagerapp/register",
					"protocol": "http",
					"host": [
						"localhost"
					],
					"port": "5040",
					"path": [
						"api",
						"taskmanagerapp",
						"register"
					]
				}
			},
			"response": []
		},
		{
			"name": "login",
			"request": {
				"method": "POST",
				"header": [],
				"body": {
					"mode": "raw",
					"raw": "{\r\n    \"username\": \"abdabdbadbadbabdfafbaf\",\r\n    \"password\":\"makaka\"\r\n\r\n}",
					"options": {
						"raw": {
							"language": "json"
						}
					}
				},
				"url": {
					"raw": "http://localhost:5040/api/taskmanagerapp/login",
					"protocol": "http",
					"host": [
						"localhost"
					],
					"port": "5040",
					"path": [
						"api",
						"taskmanagerapp",
						"login"
					]
				}
			},
			"response": []
		},
		{
			"name": "courses",
			"protocolProfileBehavior": {
				"disableBodyPruning": true
			},
			"request": {
				"method": "GET",
				"header": [],
				"body": {
					"mode": "raw",
					"raw": "",
					"options": {
						"raw": {
							"language": "json"
						}
					}
				},
				"url": {
					"raw": "http://localhost:5040/api/taskmanagerapp/courses",
					"protocol": "http",
					"host": [
						"localhost"
					],
					"port": "5040",
					"path": [
						"api",
						"taskmanagerapp",
						"courses"
					]
				}
			},
			"response": []
		},
		{
			"name": "cources",
			"protocolProfileBehavior": {
				"disableBodyPruning": true
			},
			"request": {
				"method": "GET",
				"header": [],
				"body": {
					"mode": "raw",
					"raw": "",
					"options": {
						"raw": {
							"language": "json"
						}
					}
				},
				"url": {
					"raw": "http://localhost:5040/api/taskmanagerapp/cources",
					"protocol": "http",
					"host": [
						"localhost"
					],
					"port": "5040",
					"path": [
						"api",
						"taskmanagerapp",
						"cources"
					]
				}
			},
			"response": []
		},
		{
			"name": "team",
			"protocolProfileBehavior": {
				"disableBodyPruning": true
			},
			"request": {
				"method": "GET",
				"header": [],
				"body": {
					"mode": "raw",
					"raw": "",
					"options": {
						"raw": {
							"language": "json"
						}
					}
				},
				"url": {
					"raw": "http://localhost:5040/api/taskmanagerapp/team",
					"protocol": "http",
					"host": [
						"localhost"
					],
					"port": "5040",
					"path": [
						"api",
						"taskmanagerapp",
						"team"
					]
				}
			},
			"response": []
		},
		{
			"name": "testimonial",
			"protocolProfileBehavior": {
				"disableBodyPruning": true
			},
			"request": {
				"method": "GET",
				"header": [],
				"body": {
					"mode": "raw",
					"raw": "",
					"options": {
						"raw": {
							"language": "json"
						}
					}
				},
				"url": {
					"raw": "http://localhost:5040/api/taskmanagerapp/testim",
					"protocol": "http",
					"host": [
						"localhost"
					],
					"port": "5040",
					"path": [
						"api",
						"taskmanagerapp",
						"testim"
					]
				}
			},
			"response": []
		}
	]
}